[
  {
    "name": ".NET",
    "links": [
      {
        "name": "CLI Commands",
        "href": "/dotnet/cli-commands"
      },
      {
        "name": "DataAnnotations Attributes",
        "href": "/dotnet/dataannotations-attributes"
      },
      {
        "name": "Manipulating Files",
        "href": "/dotnet/manipulating-files"
      }
    ]
  },
  {
    "name": "Patterns",
    "links": [
      {
        "name": "State Machines: Example",
        "href": "/patterns/finite-state-machines"
      },
      {
        "name": "The Observer Pattern: Example",
        "href": "/patterns/observer-pattern"
      }
    ]
  },
  {
    "name": "SQL",
    "links": [
      {
        "name": "Standard Data Types",
        "href": "/sql/standard-data-types"
      },
      {
        "name": "Standard Functions",
        "href": "/sql/standard-functions"
      }
    ]
  },
  {
    "name": "PostgreSQL",
    "links": [
      {
        "name": "Setting Up",
        "href": "/postgresql/setting-up"
      }
    ]
  },
  {
    "name": "Ubuntu Server",
    "links": [
      {
        "name": "CLI Commands",
        "href": "/ubuntu-server/cli-commands"
      },
      {
        "name": "Setting Up",
        "href": "/ubuntu-server/setting-up"
      },
      {
        "name": "Cloudflare and Nginx",
        "href": "/ubuntu-server/cloudflare-nginx"
      },
      {
        "name": "Remove Packages",
        "href": "/ubuntu-server/remove-packages"
      }
    ]
  },
  {
    "name": "Resources",
    "href": "/resources"
  }
]
